colab_markdown_editor/__init__.py
colab_markdown_editor/__main__.py
colab_markdown_editor/autosave.py
colab_markdown_editor/editor.py
colab_markdown_editor/filemgr.py
colab_markdown_editor/history.py
colab_markdown_editor/preview.py
colab_markdown_editor/toolbar.py
colab_markdown_editor-1.0.3.dist-info/licenses/LICENSE
colab_markdown_editor-1.0.3.dist-info/METADATA
colab_markdown_editor-1.0.3.dist-info/WHEEL
colab_markdown_editor-1.0.3.dist-info/entry_points.txt
colab_markdown_editor-1.0.3.dist-info/top_level.txt
colab_markdown_editor-1.0.3.dist-info/RECORD
