Metadata-Version: 2.4
Name: colab_markdown_editor
Version: 1.0.3
Summary: Interactive Markdown Editor for Google Colab Notebooks
Home-page: https://github.com/thinh-vu/colab_markdown_editor
Author: Thinh Vu
Author-email: support@vnstocks.com
License: MIT
Keywords: markdown editor google colab ipywidgets
Classifier: Development Status :: 5 - Production/Stable
Classifier: Framework :: IPython
Classifier: Intended Audience :: Developers
Classifier: Environment :: Console
Classifier: Operating System :: OS Independent
Classifier: Programming Language :: Python :: 3.11
Classifier: Topic :: Text Editors
Classifier: Topic :: Software Development :: Libraries :: Python Modules
Classifier: License :: OSI Approved :: MIT License
Requires-Python: >=3.11
License-File: LICENSE
Dynamic: author
Dynamic: author-email
Dynamic: classifier
Dynamic: description
Dynamic: description-content-type
Dynamic: home-page
Dynamic: keywords
Dynamic: license
Dynamic: license-file
Dynamic: requires-python
Dynamic: summary
